deepymod/__init__.py
deepymod/analysis/__init__.py
deepymod/analysis/load_tensorboard.py
deepymod/data/__init__.py
deepymod/data/base.py
deepymod/data/examples.py
deepymod/data/samples.py
deepymod/data/burgers/__init__.py
deepymod/data/burgers/burgers.py
deepymod/data/diffusion/__init__.py
deepymod/data/diffusion/diffusion.py
deepymod/data/kdv/__init__.py
deepymod/data/kdv/kdv.py
deepymod/model/constraint.py
deepymod/model/deepmod.py
deepymod/model/func_approx.py
deepymod/model/library.py
deepymod/model/sparse_estimators.py
deepymod/training/__init__.py
deepymod/training/convergence.py
deepymod/training/sparsity_scheduler.py
deepymod/training/training.py
deepymod/utils/logger.py
deepymod/utils/types.py
deepymod/utils/utilities.py
DeePyMoD-2.2.0.dist-info/LICENSE.txt
DeePyMoD-2.2.0.dist-info/METADATA
DeePyMoD-2.2.0.dist-info/WHEEL
DeePyMoD-2.2.0.dist-info/top_level.txt
DeePyMoD-2.2.0.dist-info/RECORD
