Metadata-Version: 2.1
Name: DeePyMoD
Version: 2.2.0
Summary: DeePyMoD is a PyTorch-based implementation of the DeepMoD algorithm for model discovery of PDEs.
Home-page: https://github.com/phimal/deepymod
Author: Gert-Jan
Author-email: gert-jan.both@cri-paris.org
License: mit
Project-URL: Documentation, https://github.com/phimal/deepymod
Platform: any
Classifier: Development Status :: 4 - Beta
Classifier: Programming Language :: Python
Requires-Python: !=3.9,>=3.6
License-File: LICENSE.txt
Requires-Dist: numpy
Requires-Dist: torch
Requires-Dist: scikit-learn
Requires-Dist: pysindy
Requires-Dist: natsort
Requires-Dist: tensorboard
Requires-Dist: matplotlib
